vovo/__ init __.py
vovo/cache/__init__.py
vovo/cache/base/__init__.py
vovo/cache/base/backend.py
vovo/cache/base/key_maker.py
vovo/cache/cache_manager.py
vovo/cache/custom_key_maker.py
vovo/cache/redis_backend.py
vovo/core/__init__.py
vovo/core/abcs.py
vovo/core/api.py
vovo/core/decorators.py
vovo/core/http/http_facotry.py
vovo/core/runnables.py
vovo/custom_logger.py
vovo/exceptions.py
vovo/kit/jwt_kit.py
vovo/monitors/__init__.py
vovo/monitors/sentry.py
vovo/persistence/__init__.py
vovo/persistence/decorators.py
vovo/persistence/models.py
vovo/persistence/repositories.py
vovo/persistence/utils.py
vovo/settings.py
vovo/utils/__init__.py
vovo/utils/async_helper.py
vovo/utils/file.py
vovo/utils/id.py
vovo/utils/image.py
vovo/utils/merge.py
vovo/utils/orm.py
vovo/utils/randoms.py
vovo/utils/strings.py
vovo/utils/type.py
vovo/utils/utils.py
vovo/web/exception_handlers.py
vovo/web/middlewares.py
vovo-0.4.6.dist-info/LICENSE
vovo-0.4.6.dist-info/METADATA
vovo-0.4.6.dist-info/WHEEL
vovo-0.4.6.dist-info/RECORD
