Metadata-Version: 2.1
Name: vovo
Version: 0.4.6
Summary: vovo base package
Author: Ark
Author-email: ark.wu@outlook.com
Requires-Python: >=3.12,<4.0
Classifier: Programming Language :: Python :: 3
Classifier: Programming Language :: Python :: 3.12
Provides-Extra: deploy
Requires-Dist: bcrypt (==4.0.1)
Requires-Dist: colorama (>=0.4.6,<0.5.0)
Requires-Dist: fastapi (>=0.115.5,<0.116.0)
Requires-Dist: httpx[http2] (>=0.28.0,<0.29.0)
Requires-Dist: motor (>=3.6.0,<3.7.0)
Requires-Dist: openpyxl (>=3.1.5,<3.2.0)
Requires-Dist: pandas (>=2.2.2,<2.3.0)
Requires-Dist: pydantic (>=2.10.2,<2.11.0)
Requires-Dist: pydantic-settings (>=2.7.1,<2.8.0)
Requires-Dist: pyjwt (>=2.10.1,<3.0.0)
Requires-Dist: python-ulid[pydantic] (>=3.0.0,<3.1.0)
Requires-Dist: redis (>=5.2.0,<5.3.0) ; extra == "deploy"
Requires-Dist: requests (>=2.32.3,<2.33.0)
Requires-Dist: sentry-sdk[fastapi] (>=2.19.0,<3.0.0)
Requires-Dist: sqlmodel (>=0.0.22,<0.1.0)
Requires-Dist: structlog (>=24.4.0,<25.0.0)
Requires-Dist: tqdm (>=4.67.1,<4.68.0)
Requires-Dist: uvicorn (>=0.34.0,<0.35.0)
